<Root_Element X="0" Y="0" WIDTH="223" HEIGHT="330" SHOWSID="5" HIDESID="4" DEFAULT_X="1" DEFAULT_Y="1" ADJUST_X="0" ADJUST_Y="0">
   <CAPTION ID="0" X="0" Y="0" WIDTH="180" HEIGHT="25"/>
   <IMAGE ID="5" X="0" Y="0" WIDTH="223" HEIGHT="27" GID="UI12_PRIVATE_STORE_CAPTION" MODULEID="0">CAPTION</IMAGE>
   <IMAGE ID="6" X="0" Y="26" WIDTH="223" HEIGHT="69" GID="UI12_PRIVATE_STORE_TOP" MODULEID="0">STORE_TABS</IMAGE>
   <IMAGE ID="8" X="0" Y="94" WIDTH="223" HEIGHT="41" GID="UI12_PRIVATE_STORE_MIDDLE" MODULEID="0">STORE_MIDDLE</IMAGE>
   <IMAGE ID="8" X="0" Y="134" WIDTH="223" HEIGHT="41" GID="UI12_PRIVATE_STORE_MIDDLE" MODULEID="0">STORE_MIDDLE</IMAGE>
   <IMAGE ID="8" X="0" Y="174" WIDTH="223" HEIGHT="41" GID="UI12_PRIVATE_STORE_MIDDLE" MODULEID="0">STORE_MIDDLE</IMAGE>
   <IMAGE ID="8" X="0" Y="214" WIDTH="223" HEIGHT="41" GID="UI12_PRIVATE_STORE_MIDDLE" MODULEID="0">STORE_MIDDLE</IMAGE>
   <IMAGE ID="9" X="0" Y="254" WIDTH="223" HEIGHT="77" GID="UI12_PRIVATE_STORE_BOTTOM" MODULEID="0">STORE_BOTTOM</IMAGE>
   <BUTTON ID="20" X="203" Y="4" WIDTH="18" HEIGHT="18" NORMALGID="UI07_BTN_CLOSE_NORMAL" OVERGID="UI07_BTN_CLOSE_OVER" DOWNGID="UI07_BTN_CLOSE_DOWN" MODULEID="0">CLOSE</BUTTON>
   <RADIOBOX ID="30"/>
   <RADIOBUTTON ID="32" X="76" Y="26" WIDTH="70" HEIGHT="20" NORMALGID="UI12_BTN_BUY_NORMAL" OVERGID="UI12_BTN_BUY_OVER" DOWNGID="UI12_BTN_BUY_DOWN" MODULEID="0" RADIOBOXID="30">BUY BTN</RADIOBUTTON>
   <RADIOBUTTON ID="31" X="6" Y="26" WIDTH="70" HEIGHT="20" NORMALGID="UI12_BTN_SELL_NORMAL" OVERGID="UI12_BTN_SELL_OVER" DOWNGID="UI12_BTN_SELL_DOWN" MODULEID="0" RADIOBOXID="30">SELL BTN</RADIOBUTTON>
</Root_Element>
